flask_milligram/__init__.py
flask_milligram/static/css/milligram-extensions.css
flask_milligram/static/css/milligram-extensions.min.css
flask_milligram/static/css/milligram.css
flask_milligram/static/css/milligram.min.css
flask_milligram/static/css/normalize.css
flask_milligram/static/css/normalize.min.css
flask_milligram/static/js/milligram-extensions.js
flask_milligram/templates/milligram/nav.html
flask_milligram/templates/milligram/pagination.html
flask_milligram/templates/milligram/utilities.html
Flask_Milligram-0.1.0.dist-info/LICENSE
Flask_Milligram-0.1.0.dist-info/METADATA
Flask_Milligram-0.1.0.dist-info/WHEEL
Flask_Milligram-0.1.0.dist-info/top_level.txt
Flask_Milligram-0.1.0.dist-info/RECORD
